birfycat/__init__.py
birfycat-1.0.dist-info/METADATA
birfycat-1.0.dist-info/RECORD
birfycat-1.0.dist-info/WHEEL
birfycat-1.0.dist-info/entry_points.txt
birfycat-1.0.dist-info/top_level.txt
