Metadata-Version: 2.1
Name: birfycat
Version: 1.0
Summary: Virtual cat
Home-page: https://www.birfied.com
Author: zzcdy
Author-email: 15302010010@fudan.edu.cn
License: UNKNOWN
Platform: UNKNOWN
